felyne-7.0.4.dist-info/METADATA
felyne-7.0.4.dist-info/RECORD
felyne-7.0.4.dist-info/WHEEL
felyne-7.0.4.dist-info/top_level.txt
kytten/__init__.py
kytten/button.py
kytten/checkbox.py
kytten/dialog.py
kytten/document.py
kytten/file_dialogs.py
kytten/frame.py
kytten/layout.py
kytten/menu.py
kytten/override.py
kytten/safe_eval.py
kytten/scrollable.py
kytten/scrollbar.py
kytten/slider.py
kytten/text_input.py
kytten/theme.py
kytten/widgets.py
kytten/window.py
kytten/themes/__init__.py
kytten/themes/classic/book-open.png
kytten/themes/classic/book.png
kytten/themes/classic/button-down.png
kytten/themes/classic/button-highlight.png
kytten/themes/classic/button.png
kytten/themes/classic/checkbox-checked.png
kytten/themes/classic/checkbox.png
kytten/themes/classic/dropdown.png
kytten/themes/classic/hscrollbar.png
kytten/themes/classic/input-highlight.png
kytten/themes/classic/input.png
kytten/themes/classic/line.png
kytten/themes/classic/panel.png
kytten/themes/classic/pulldown.png
kytten/themes/classic/slider-bar.png
kytten/themes/classic/slider-knob.png
kytten/themes/classic/slider-step.png
kytten/themes/classic/theme.json
kytten/themes/classic/titlepanel.png
kytten/themes/classic/vscrollbar.png
kytten/themes/felyne/book-open.png
kytten/themes/felyne/book.png
kytten/themes/felyne/button-down.png
kytten/themes/felyne/button-highlight.png
kytten/themes/felyne/button.png
kytten/themes/felyne/checkbox-checked.png
kytten/themes/felyne/checkbox.png
kytten/themes/felyne/dropdown.png
kytten/themes/felyne/hscrollbar.png
kytten/themes/felyne/input-highlight.png
kytten/themes/felyne/input.png
kytten/themes/felyne/line.png
kytten/themes/felyne/panel.png
kytten/themes/felyne/pulldown.png
kytten/themes/felyne/slider-bar.png
kytten/themes/felyne/slider-knob.png
kytten/themes/felyne/slider-step.png
kytten/themes/felyne/theme.json
kytten/themes/felyne/titlepanel.png
kytten/themes/felyne/vscrollbar.png
kytten/themes/simplui/book-open.png
kytten/themes/simplui/book.png
kytten/themes/simplui/button-down.png
kytten/themes/simplui/button-highlight.png
