Metadata-Version: 2.1
Name: felyne
Version: 7.0.4
Summary: A Python 3 fork of Kytten, a widget toolkit for Pyglet.
Home-page: https://github.com/DeflatedPickle/felyne
Author: Conrad 'Lynx' Wong (originator), Raymond Chandler III (fork), DeflatedPickle (fork)
Author-email: UNKNOWN
License: BSD
Platform: UNKNOWN
Classifier: Development Status :: 5 - Production/Stable
Classifier: Environment :: MacOS X
Classifier: Environment :: Win32 (MS Windows)
Classifier: Environment :: X11 Applications
Classifier: Intended Audience :: Developers
Classifier: License :: OSI Approved :: BSD License
Classifier: Natural Language :: English
Classifier: Operating System :: MacOS :: MacOS X
Classifier: Operating System :: Microsoft :: Windows
Classifier: Operating System :: POSIX :: Linux
Classifier: Programming Language :: Python
Classifier: Topic :: Software Development :: Libraries :: Python Modules
Classifier: Topic :: Games/Entertainment
Requires-Dist: pyglet (>=1.1.4)
